{
  "form-sign-in-using-mobile-number":"Login with your mobile number",
  "label-phone-number-required":"Phone number",
  "placeholder-phone-number":"Enter your phone number",
  "phone-number-required":"You must need to provide your phone number",
  "error-phone-number":"Please provide valid phone number",
  "button-send-otp":"",
  "button-resend-otp":"",
  "button-send-otp-on-call":"",
  "label-otp-required":"OTP",
  "placeholder-otp":"Please provide OTP send to phone number",
  "otp-required":"You must need to provide your OTP",
  "error-otp":"Please provide valid OTP",
  "label-remember-me": "Remember me",
  "button-login-using-mobile-number":"Login",

  "form-update-user-details":"",
  "label-name-required":"Name (required)",
  "placeholder-name":"Enter Your Name",
  "name-required":"You must need to provide your name",
  "error-name" : "",
  "label-email":"Email",
  "placeholder-email":"Enter Your Email address",
  "error-email":"Please provide valid Email address",
  "label-gender-required":"Gender (required)",
  "placeholder-gender":"Select your gender",
  "gender-required":"You must need to provide your gender",
  "label-email-otp-required":"OTP (required)",
  "placeholder-email-otp":"Please provide OTP sent to your mail",
  "email-otp-required":"You must need to provide your OTP",
  "error-email-otp":"Please provide valid OTP",
  "button-update-user-details":"",

  "form-contact-us":"",
  "lable-email-required":"Email (required)",
  "email-required":"You must need to provide your Email address",
  "label-subject-required":"Subject *",
  "placeholder-subject":"Please provide your subject",
  "subject-required":"You must need to provide your subject",
  "error-subject":"Please provide a valid subject",
  "label-message":"Message",
  "placeholder-message":"Enter Your message",
  "button-send-message":"Send Message",

  "form-add-an-address":"",
  "label-door-no-required":"Door No (required)",
  "placeholder-door-no":"Enter Your door No.",
  "door-no-required":"You must need to provide your door number",
  "label-location-name-required":"Location (required)",
  "placeholder-location-name":"Enter Your location",
  "location-name-required":"You must need to provide your location",
  "label-landmark":"Landmark",
  "placeholder-landmark":"Enter Your location landmark",
  "label-city-name-required":"City (required)",
  "city-name-required":"You must need to provide your city",
  "placeholder-city-name":"Enter Your city",
  "lable-state-name-required":"State (required)",
  "placeholder-state-name":"Enter Your state",
  "state-name-required":"You must need to provide your state",
  "error-state-name":"Please provide a valid state",
  "label-pincode-required":"Pincode (required)",
  "placeholder-pincode":"Enter Your area pincode",
  "pincode-required":"You must need to provide your area pincode",
  "error-pincode":"Please provide a valid pincode",
  "label-alternate-phone-number":"Alternate Phone Number (required)",
  "placeholder-alternate-phone-number":"Enter your alternate phone number",
  "label-address-type-required":"Address type (required)",
  "address-type-required":"You must need to provide type of your address",
  "button-add-address":"",
  "button-update-address":"",



  "form-write-a-review":"",
  "label-review-title":"Review title",
  "placeholder-review-title":"Enter your review title",
  "error-review-title":"Review title must contain atleast2 characters",
  "label-review-description":"Description (required)",
  "placeholder-review-description":"Enter your review description",
  "error-review-description":"Review title must contain atleast 5 characters",

  "form-ask-a-question":"",
  "label-question-required":"Question (required)",
  "placeholder-question":"Enter your question",
  "question-required":"You must need to provide a question",
  "error-question":"Question must contain atleast 5 characters",


  "form-answer-a-question":"",
  "label-answer-required":"Answer (required)",
  "placeholder-answer":"Enter your answer",
  "answer-required":"You must need to provide a answer",
  "error-answer":"answer must contain atleast 5 characters",


  "form-subscribe" : "",
  "placeholder-email-subscribe": "Write your email here",

  "placeholder-search": "Search..."
}